graphene/__init__.py
graphene_mlx-0.1.0.dist-info/LICENSE
graphene_mlx-0.1.0.dist-info/METADATA
graphene_mlx-0.1.0.dist-info/WHEEL
graphene_mlx-0.1.0.dist-info/top_level.txt
graphene_mlx-0.1.0.dist-info/RECORD
