Metadata-Version: 2.1
Name: graphene-mlx
Version: 0.1.0
Summary: Neural Network Trainer for MLX
Author-email: Petru Radulescu <petruradulescu.v@gmail.com>
License: Apache License, Version 2.0
Requires-Python: >=3.10
License-File: LICENSE
Requires-Dist: mlx
Requires-Dist: mlx-data
Requires-Dist: setuptools
Requires-Dist: tqdm
Requires-Dist: wandb
Provides-Extra: dev
Requires-Dist: black >=23.7.0 ; extra == 'dev'
Requires-Dist: ruff >=0.0.282 ; extra == 'dev'
Requires-Dist: pre-commit >=3.3.0 ; extra == 'dev'
Requires-Dist: pip-tools ; extra == 'dev'
Requires-Dist: pyright ; extra == 'dev'
Requires-Dist: ruff-lsp ; extra == 'dev'
